{
    "inputs": [
        {
            "id": 1, "type": "Аналоговый", "depthIntegration": "100", "display": true
        },
        {
            "id": 2, "type": "Реллейный", "depthIntegration": "110", "display": true
        },
        {
            "id": 3, "type": "Реллейный", "depthIntegration": "120", "display": true
        },
        {
            "id": 4, "type": "Аналоговый", "depthIntegration": "80", "display": true
        },
        {
            "id": 5, "type": "Аналоговый", "depthIntegration": "50", "display": true
        }
    ],
    "outputs": [
        {
            "id": 1, "type": "Аналоговый", "sum": 10, "min": 1, "max": 15, "display": true, "threshold": 60
        },
        {
            "id": 2, "sum": 10, "type": "Реллейный", "min": 1, "max": 15, "display": true, "threshold": 0
        }
    ],
    "profiles": [
        {
            "value": "winter",
            "active": true
        },
        {
            "value": "summer",
            "active": false
        }
    ]
}